{ "name": "Virgil Thomson", "gender": "Male", "area": "United States", "deleted": false, "mbid": "0b0e4a44-b090-4f78-8db9-376dc32f407f", "_id": "0b0e4a44-b090-4f78-8db9-376dc32f407f", "slug_name": "virgil-thomson", "slug_postfix": { "$numberLong": 0 }, "ISNI": "0000000109192182", "MBID": "0b0e4a44-b090-4f78-8db9-376dc32f407f", "disambiguation_comment": "", "albums": [], "profile_image_url": "https://upload.wikimedia.org/wikipedia/commons/4/40/Virgilthomson.jpg", "images_urls": [], "begin_date": { "$dateDay": "1896-11-25" }, "end_date": { "$dateDay": "1989-09-30" }, "rating": 2.703125 }
