{ "name": "Penetrante Sorte", "gender": "\\N", "area": "Austria", "deleted": false, "mbid": "0d5c8c96-0469-44ac-985e-105f2f0c43c7", "_id": "0d5c8c96-0469-44ac-985e-105f2f0c43c7", "slug_name": "penetrante-sorte", "slug_postfix": { "$numberLong": 0 }, "MBID": "0d5c8c96-0469-44ac-985e-105f2f0c43c7", "disambiguation_comment": "", "albums": [], "profile_image_url": "https://upload.wikimedia.org/wikipedia/commons/d/d1/Penetrante_Sorte_Foto2.jpg", "images_urls": [], "begin_date": { "$dateDay": "2002-01-01" }, "rating": 2.824324324324324 }
