{ "name": "Ola Gjeilo", "gender": "Male", "area": "Norway", "deleted": false, "mbid": "161b32e2-2c37-4445-9087-a597ebcd0fd4", "_id": "161b32e2-2c37-4445-9087-a597ebcd0fd4", "slug_name": "ola-gjeilo", "slug_postfix": { "$numberLong": 0 }, "IPI": "00274501771", "ISNI": "0000000084159502", "MBID": "161b32e2-2c37-4445-9087-a597ebcd0fd4", "disambiguation_comment": "", "albums": [], "profile_image_url": "http://olagjeilo.com/admin/wp-content/uploads/Ola-Gjeilo-Picture-3.jpg", "images_urls": [], "begin_date": { "$dateDay": "1978-05-05" }, "rating": 2.338709677419355 }
