{ "name": "Галина Кривошапко", "gender": "Female", "area": "Russia", "deleted": false, "mbid": "1de92313-659b-4490-9d24-a9d6b58edd99", "_id": "1de92313-659b-4490-9d24-a9d6b58edd99", "slug_name": "galina-krivosapko", "slug_postfix": { "$numberLong": 0 }, "MBID": "1de92313-659b-4490-9d24-a9d6b58edd99", "disambiguation_comment": "", "albums": [], "profile_image_url": "http://img.inforotor.ru/news/300x300/9301700.jpg", "images_urls": [], "begin_date": { "$dateDay": "1916-06-17" }, "end_date": { "$dateDay": "2013-02-06" }, "rating": 2.46 }
