{ "name": "Traudel Haas", "gender": "Female", "area": "\\N", "deleted": false, "mbid": "23cde45d-bc0b-4d5b-9c1d-7840a62a44a0", "_id": "23cde45d-bc0b-4d5b-9c1d-7840a62a44a0", "slug_name": "traudel-haas", "slug_postfix": { "$numberLong": 0 }, "MBID": "23cde45d-bc0b-4d5b-9c1d-7840a62a44a0", "disambiguation_comment": "deutsche Schauspielerin und Synchronsprecherin", "albums": [], "profile_image_url": "https://upload.wikimedia.org/wikipedia/commons/c/ca/Traudel_Haas_04_2010.JPG", "images_urls": [], "begin_date": { "$dateDay": "1945-09-03" }, "rating": 2.6739130434782608 }
