{ "name": "DJ Apollo", "gender": "\\N", "area": "\\N", "deleted": false, "mbid": "260fed04-8ffd-46e5-9787-51d68e31edcf", "_id": "260fed04-8ffd-46e5-9787-51d68e31edcf", "slug_name": "dj-apollo", "slug_postfix": { "$numberLong": 0 }, "MBID": "260fed04-8ffd-46e5-9787-51d68e31edcf", "disambiguation_comment": "Hip-hop DJ member of Buckshot LeFonque & Triple Threat", "albums": [], "profile_image_url": "http://www.fatbeats.com/.scm.library/photo_.78926198973be987.jpeg", "images_urls": [], "begin_date": { "$dateDay": "1969-11-20" }, "rating": 2.689655172413793 }
