{ "name": "Jennifer Warnes", "gender": "Female", "area": "United States", "deleted": false, "mbid": "2f140aa6-b99b-4f79-ae33-96018af87fa3", "_id": "2f140aa6-b99b-4f79-ae33-96018af87fa3", "slug_name": "jennifer-warnes", "slug_postfix": { "$numberLong": 0 }, "ISNI": "0000000073662348", "MBID": "2f140aa6-b99b-4f79-ae33-96018af87fa3", "disambiguation_comment": "", "albums": [], "profile_image_url": "https://commons.wikimedia.org/wiki/File:Jennifer_Warnes_(David_Alexander).jpg", "images_urls": [], "begin_date": { "$dateDay": "1947-03-03" }, "rating": 2.619047619047619 }
