{ "name": "Kylie Minogue", "gender": "Female", "area": "Australia", "deleted": false, "mbid": "2fddb92d-24b2-46a5-bf28-3aed46f4684c", "_id": "2fddb92d-24b2-46a5-bf28-3aed46f4684c", "slug_name": "kylie-minogue", "slug_postfix": { "$numberLong": 0 }, "IPI": "00165433375", "ISNI": "0000000080162464", "MBID": "2fddb92d-24b2-46a5-bf28-3aed46f4684c", "disambiguation_comment": "", "albums": [], "profile_image_url": "https://upload.wikimedia.org/wikipedia/commons/a/a8/Kylie_Minogue_Cannes.jpg", "images_urls": [], "begin_date": { "$dateDay": "1968-05-28" }, "rating": 2.8541666666666665 }
