{ "name": "Azam Ali", "gender": "Female", "area": "Canada", "deleted": false, "mbid": "347aafad-0d39-4046-8455-21da93854943", "_id": "347aafad-0d39-4046-8455-21da93854943", "slug_name": "azam-ali", "slug_postfix": { "$numberLong": 0 }, "ISNI": "0000000055494141", "MBID": "347aafad-0d39-4046-8455-21da93854943", "disambiguation_comment": "", "albums": [], "profile_image_url": "https://upload.wikimedia.org/wikipedia/commons/4/41/Azam_Ali_2005-09-17_Kavehaz_NY.jpg", "images_urls": [], "begin_date": { "$dateDay": "1970-01-01" }, "rating": 2.890625 }
