{ "name": "Jörg Mager", "gender": "Male", "area": "Germany", "deleted": false, "mbid": "3caf9c6b-b644-43b4-a026-5f4c119f03f0", "_id": "3caf9c6b-b644-43b4-a026-5f4c119f03f0", "slug_name": "jorg-mager", "slug_postfix": { "$numberLong": 0 }, "MBID": "3caf9c6b-b644-43b4-a026-5f4c119f03f0", "disambiguation_comment": "", "albums": [], "profile_image_url": "https://upload.wikimedia.org/wikipedia/commons/f/f1/J%C3%B6rg_Mager_playing_on_Spherophone.jpg", "images_urls": [], "begin_date": { "$dateDay": "1880-01-01" }, "end_date": { "$dateDay": "1939-04-05" }, "rating": 3.1875 }
