{ "name": "Yasi Hofer", "gender": "Female", "area": "Germany", "deleted": false, "mbid": "3f1c3068-3dd4-4e50-a645-65192626f66b", "_id": "3f1c3068-3dd4-4e50-a645-65192626f66b", "slug_name": "yasi-hofer", "slug_postfix": { "$numberLong": 0 }, "MBID": "3f1c3068-3dd4-4e50-a645-65192626f66b", "disambiguation_comment": "", "albums": [], "profile_image_url": "https://upload.wikimedia.org/wikipedia/commons/6/64/Yasi-hofer.jpg", "images_urls": [], "begin_date": { "$dateDay": "1992-10-01" }, "rating": 3.0606060606060606 }
