{ "name": "Michael William Balfe", "gender": "Male", "area": "Ireland", "deleted": false, "mbid": "464bde73-2fc8-47e2-a7c1-dc3e98640714", "_id": "464bde73-2fc8-47e2-a7c1-dc3e98640714", "slug_name": "michael-william-balfe", "slug_postfix": { "$numberLong": 0 }, "ISNI": "0000000107843447", "MBID": "464bde73-2fc8-47e2-a7c1-dc3e98640714", "disambiguation_comment": "", "albums": [], "profile_image_url": "https://commons.wikimedia.org/wiki/File:Michael_William_Balfe.jpg", "images_urls": [], "begin_date": { "$dateDay": "1808-05-15" }, "end_date": { "$dateDay": "1870-10-20" }, "rating": 2.435483870967742 }
