{ "name": "INXS", "gender": "\\N", "area": "Australia", "deleted": false, "mbid": "481bf5f9-2e7c-4c44-b08a-05b32bc7c00d", "_id": "481bf5f9-2e7c-4c44-b08a-05b32bc7c00d", "slug_name": "inxs", "slug_postfix": { "$numberLong": 0 }, "ISNI": "0000000119404740", "MBID": "481bf5f9-2e7c-4c44-b08a-05b32bc7c00d", "disambiguation_comment": "", "albums": [], "profile_image_url": "https://upload.wikimedia.org/wikipedia/commons/3/3d/INXS.jpg", "images_urls": [], "begin_date": { "$dateDay": "1977-08-16" }, "end_date": { "$dateDay": "2012-11-13" }, "rating": 2.6666666666666665 }
