{ "name": "H. C. Artmann", "gender": "Male", "area": "Austria", "deleted": false, "mbid": "48a8060e-ff21-4df6-b6df-c76a509139be", "_id": "48a8060e-ff21-4df6-b6df-c76a509139be", "slug_name": "h-c-artmann", "slug_postfix": { "$numberLong": 0 }, "IPI": "00001432645", "ISNI": "0000000110690218", "MBID": "48a8060e-ff21-4df6-b6df-c76a509139be", "disambiguation_comment": "", "albums": [], "profile_image_url": "https://upload.wikimedia.org/wikipedia/commons/c/c6/H.C._Artmann_19741121_Triptychon.jpg", "images_urls": [], "begin_date": { "$dateDay": "1921-06-12" }, "end_date": { "$dateDay": "2000-12-04" }, "rating": 3.4 }
