{ "name": "Tricky", "gender": "Male", "area": "United Kingdom", "deleted": false, "mbid": "5bf64d94-efd9-4334-96fd-e6197b0b02b8", "_id": "5bf64d94-efd9-4334-96fd-e6197b0b02b8", "slug_name": "tricky", "slug_postfix": { "$numberLong": 0 }, "IPI": "00248974221", "ISNI": "0000000118100972", "MBID": "5bf64d94-efd9-4334-96fd-e6197b0b02b8", "disambiguation_comment": "UK trip hop producer Adrian Thaws", "albums": [], "profile_image_url": "https://upload.wikimedia.org/wikipedia/commons/7/7f/Tricky_-_August_13%2C_2009.jpg", "images_urls": [], "begin_date": { "$dateDay": "1968-01-27" }, "rating": 2.95 }
