{ "name": "James Horner", "gender": "Male", "area": "United States", "deleted": false, "mbid": "679ec43c-bc04-4bb0-b619-2da702a214ba", "_id": "679ec43c-bc04-4bb0-b619-2da702a214ba", "slug_name": "james-horner", "slug_postfix": { "$numberLong": 0 }, "IPI": "00076160186", "ISNI": "0000000121196004", "MBID": "679ec43c-bc04-4bb0-b619-2da702a214ba", "disambiguation_comment": "", "albums": [ { "cover_image_url": "http://coverartarchive.org/release/bfc5f730-32e8-4798-b231-7a665bd7199b/16419895668.jpg", "slug": "humanoids-from-the-deep-original-motion-picture-soundtrack-0", "name": "Humanoids from the Deep (Original Motion Picture Soundtrack)", "id": "bfc5f730-32e8-4798-b231-7a665bd7199b" } ], "profile_image_url": "https://commons.wikimedia.org/wiki/File:James_Horner_2015.jpg", "images_urls": [], "begin_date": { "$dateDay": "1953-08-14" }, "end_date": { "$dateDay": "2015-06-22" }, "rating": 2.7241379310344827 }
