{ "name": "Viggo Bielefeldt", "gender": "Male", "area": "Denmark", "deleted": false, "mbid": "700bff98-277f-40d7-aeaa-97758b3f5667", "_id": "700bff98-277f-40d7-aeaa-97758b3f5667", "slug_name": "viggo-bielefeldt", "slug_postfix": { "$numberLong": 0 }, "MBID": "700bff98-277f-40d7-aeaa-97758b3f5667", "disambiguation_comment": "", "albums": [], "profile_image_url": "https://upload.wikimedia.org/wikipedia/commons/3/30/Viggo_Emil_Bielefeldt.gif", "images_urls": [], "begin_date": { "$dateDay": "1851-10-16" }, "end_date": { "$dateDay": "1909-12-17" }, "rating": 3.2857142857142856 }
