{ "name": "IIndman", "gender": "Male", "area": "South Africa", "deleted": false, "mbid": "7dc68424-c00f-400a-be1a-46b4dcc34f6b", "_id": "7dc68424-c00f-400a-be1a-46b4dcc34f6b", "slug_name": "iindman", "slug_postfix": { "$numberLong": 0 }, "MBID": "7dc68424-c00f-400a-be1a-46b4dcc34f6b", "disambiguation_comment": "Phenyo Kgaffe", "albums": [], "profile_image_url": "https://upload.wikimedia.org/wikipedia/commons/1/1c/IIndMan_01.jpg", "images_urls": [], "begin_date": { "$dateDay": "1992-11-25" }, "rating": 2.8378378378378377 }
