{ "name": "安室奈美恵", "gender": "Female", "area": "Japan", "deleted": false, "mbid": "888994e5-6f53-4f53-bced-b20482aea42a", "_id": "888994e5-6f53-4f53-bced-b20482aea42a", "slug_name": "an-shi-nai-mei-hui", "slug_postfix": { "$numberLong": 0 }, "ISNI": "0000000041171384", "MBID": "888994e5-6f53-4f53-bced-b20482aea42a", "disambiguation_comment": "", "albums": [], "profile_image_url": "https://commons.wikimedia.org/wiki/File:Namie_Amuro_MAA.JPG", "images_urls": [], "begin_date": { "$dateDay": "1977-09-20" }, "rating": 2.65 }
