{ "name": "Pentti Saaritsa", "gender": "Male", "area": "Finland", "deleted": false, "mbid": "8de89aef-42f0-4720-869e-89c94bf39065", "_id": "8de89aef-42f0-4720-869e-89c94bf39065", "slug_name": "pentti-saaritsa", "slug_postfix": { "$numberLong": 0 }, "MBID": "8de89aef-42f0-4720-869e-89c94bf39065", "disambiguation_comment": "", "albums": [], "profile_image_url": "https://commons.wikimedia.org/wiki/File:Pentti_Saaritsa.jpg", "images_urls": [], "begin_date": { "$dateDay": "1941-12-29" }, "rating": 2.706896551724138 }
