{ "name": "Juli Zeh", "gender": "Female", "area": "Germany", "deleted": false, "mbid": "9ca31944-c8ab-4318-b323-cf8c470eeff3", "_id": "9ca31944-c8ab-4318-b323-cf8c470eeff3", "slug_name": "juli-zeh", "slug_postfix": { "$numberLong": 0 }, "ISNI": "0000000121489034", "MBID": "9ca31944-c8ab-4318-b323-cf8c470eeff3", "disambiguation_comment": "", "albums": [ { "cover_image_url": "http://coverartarchive.org/release/25687f55-7064-409d-8b99-642ad907e92a/12930633544.jpg", "slug": "adler-und-engel-0", "name": "Adler und Engel", "id": "25687f55-7064-409d-8b99-642ad907e92a" } ], "profile_image_url": "https://commons.wikimedia.org/wiki/File:Julie_Zeh.JPG", "images_urls": [], "begin_date": { "$dateDay": "1974-06-30" }, "rating": 2.3620689655172415 }
