{ "name": "Salim Dada", "gender": "Male", "area": "Algeria", "deleted": false, "mbid": "a771d4f7-35bc-427f-a1c9-9f0c185518ea", "_id": "a771d4f7-35bc-427f-a1c9-9f0c185518ea", "slug_name": "salim-dada", "slug_postfix": { "$numberLong": 0 }, "MBID": "a771d4f7-35bc-427f-a1c9-9f0c185518ea", "disambiguation_comment": "", "albums": [], "profile_image_url": "https://upload.wikimedia.org/wikipedia/commons/1/13/Salim_DADA.JPG", "images_urls": [], "begin_date": { "$dateDay": "1975-01-01" }, "rating": 3.109375 }
