{ "name": "Tina Arena", "gender": "Female", "area": "Australia", "deleted": false, "mbid": "c1ccc784-9f18-4369-96b1-38106419b5ad", "_id": "c1ccc784-9f18-4369-96b1-38106419b5ad", "slug_name": "tina-arena", "slug_postfix": { "$numberLong": 0 }, "ISNI": "0000000078400873", "MBID": "c1ccc784-9f18-4369-96b1-38106419b5ad", "disambiguation_comment": "", "albums": [], "profile_image_url": "https://upload.wikimedia.org/wikipedia/commons/1/13/Tina_Arena_2013.jpg", "images_urls": [], "begin_date": { "$dateDay": "1967-11-01" }, "rating": 2.7 }
