{ "name": "Bob Marley & The Wailers", "gender": "\\N", "area": "Jamaica", "deleted": false, "mbid": "c296e10c-110a-4103-9e77-47bfebb7fb2e", "_id": "c296e10c-110a-4103-9e77-47bfebb7fb2e", "slug_name": "bob-marley--the-wailers", "slug_postfix": { "$numberLong": 0 }, "IPI": "00034755283", "ISNI": "0000000122768131", "MBID": "c296e10c-110a-4103-9e77-47bfebb7fb2e", "disambiguation_comment": "", "albums": [], "profile_image_url": "https://upload.wikimedia.org/wikipedia/commons/6/61/Bob-marley-wailers-crystal-palace.jpg", "images_urls": [], "begin_date": { "$dateDay": "1970-12-01" }, "end_date": { "$dateDay": "1981-05-11" }, "rating": 2.3653846153846154 }
