{ "name": "Ottavio Dantone", "gender": "Male", "area": "Italy", "deleted": false, "mbid": "c4787634-90ec-4cef-b2cc-aa7536625570", "_id": "c4787634-90ec-4cef-b2cc-aa7536625570", "slug_name": "ottavio-dantone", "slug_postfix": { "$numberLong": 0 }, "ISNI": "0000000055191757", "MBID": "c4787634-90ec-4cef-b2cc-aa7536625570", "disambiguation_comment": "", "albums": [], "profile_image_url": "https://upload.wikimedia.org/wikipedia/commons/b/be/Ottavio_Dantone3.jpg", "images_urls": [], "begin_date": { "$dateDay": "1960-10-09" }, "rating": 2.90625 }
