{"name":"LAL","gender":"\\N","area":"Canada","deleted":false,"mbid":"c8db33c4-ecd4-474e-8cbe-8c5324c14f07","_id":"c8db33c4-ecd4-474e-8cbe-8c5324c14f07","slug_name":"lal","slug_postfix":{"$numberLong":0},"MBID":"c8db33c4-ecd4-474e-8cbe-8c5324c14f07","disambiguation_comment":"Toronto world music collective","albums":[{"cover_image_url":"http://coverartarchive.org/release/7e334e25-3d3e-4e48-aae9-455d57714b70/15335704836.jpg","slug":"warm-belly-high-power-0","name":"Warm Belly High Power","id":"7e334e25-3d3e-4e48-aae9-455d57714b70"}],"profile_image_url":"https://i.vimeocdn.com/portrait/12231773.webp","images_urls":["https://pbs.twimg.com/media/C4Z0VzKWMAMbptI.jpg:large"],"rating":3.2758620689655173}
