{ "name": "SGLIS", "gender": "Male", "area": "Peru", "deleted": false, "mbid": "d3f29741-9b9f-46c0-bcbe-d2636d028cd9", "_id": "d3f29741-9b9f-46c0-bcbe-d2636d028cd9", "slug_name": "sglis", "slug_postfix": { "$numberLong": 0 }, "MBID": "d3f29741-9b9f-46c0-bcbe-d2636d028cd9", "disambiguation_comment": "", "albums": [], "profile_image_url": "https://es.wikiquote.org/wiki/SGLIS#/media/File:SGLIS_en_bellavista_nuevo_chimbote.jpg", "images_urls": [], "begin_date": { "$dateDay": "1990-06-13" }, "rating": 2.5625 }
