{ "name": "Mario Bauzá", "gender": "Male", "area": "United States", "deleted": false, "mbid": "da951c78-737f-4e7a-b7fd-17297bdae3c0", "_id": "da951c78-737f-4e7a-b7fd-17297bdae3c0", "slug_name": "mario-bauza", "slug_postfix": { "$numberLong": 0 }, "ISNI": "0000000059363528", "MBID": "da951c78-737f-4e7a-b7fd-17297bdae3c0", "disambiguation_comment": "", "albums": [], "profile_image_url": "https://upload.wikimedia.org/wikipedia/commons/f/f6/Mario_Bauz%C3%A1.jpg", "images_urls": [], "begin_date": { "$dateDay": "1911-04-28" }, "end_date": { "$dateDay": "1993-07-11" }, "rating": 2.546875 }
