{ "name": "Tommy Makem", "gender": "Male", "area": "United States", "deleted": false, "mbid": "ed29f6fa-ca96-47f7-9c7e-b9f2f11f30e4", "_id": "ed29f6fa-ca96-47f7-9c7e-b9f2f11f30e4", "slug_name": "tommy-makem", "slug_postfix": { "$numberLong": 0 }, "ISNI": "0000000115701174", "MBID": "ed29f6fa-ca96-47f7-9c7e-b9f2f11f30e4", "disambiguation_comment": "", "albums": [], "profile_image_url": "https://upload.wikimedia.org/wikipedia/commons/a/a2/TommyMakem_DublinOhio.jpg", "images_urls": [], "begin_date": { "$dateDay": "1932-11-04" }, "end_date": { "$dateDay": "2007-08-01" }, "rating": 2.880952380952381 }
