{ "name": "Calypso Rose", "gender": "Female", "area": "Trinidad and Tobago", "deleted": false, "mbid": "ed4a6b66-f07f-41cb-9e5d-ea47d40beba6", "_id": "ed4a6b66-f07f-41cb-9e5d-ea47d40beba6", "slug_name": "calypso-rose", "slug_postfix": { "$numberLong": 0 }, "MBID": "ed4a6b66-f07f-41cb-9e5d-ea47d40beba6", "disambiguation_comment": "", "albums": [], "profile_image_url": "https://upload.wikimedia.org/wikipedia/commons/4/46/Calypso_rose.jpg", "images_urls": [], "begin_date": { "$dateDay": "1940-04-27" }, "rating": 2.5588235294117645 }
