{ "name": "소년공화국", "gender": "\\N", "area": "South Korea", "deleted": false, "mbid": "0736fc82-af25-4eee-ac3c-0354b873a2ed", "_id": "0736fc82-af25-4eee-ac3c-0354b873a2ed", "slug_name": "sonyeongonghwagug", "slug_postfix": { "$numberLong": 0 }, "MBID": "0736fc82-af25-4eee-ac3c-0354b873a2ed", "disambiguation_comment": "", "albums": [], "profile_image_url": "https://upload.wikimedia.org/wikipedia/commons/e/e9/%28%EC%8B%B9%ED%8A%9C%EB%B8%8C%29_SAC_%EB%B0%A9%EC%86%A1%EB%8C%84%EC%8A%A4%EA%B3%BC_%EC%A1%B8%EC%97%85%EB%B0%9C%ED%91%9C%ED%9A%8C_%EC%B6%95%ED%95%98%EB%A9%94%EC%84%B8%EC%A7%80_%28%EC%86%8C%EB%85%84%EA%B3%B5%ED%99%94%EA%B5%AD%29.jpg", "images_urls": [], "begin_date": { "$dateDay": "2013-01-01" }, "rating": 2.824324324324324 }
