{ "name": "吳國敬", "gender": "Male", "area": "Hong Kong", "deleted": false, "mbid": "075a4c83-3e79-492d-8de3-f13d0924adf9", "_id": "075a4c83-3e79-492d-8de3-f13d0924adf9", "slug_name": "wu-guo-jing", "slug_postfix": { "$numberLong": 0 }, "MBID": "075a4c83-3e79-492d-8de3-f13d0924adf9", "disambiguation_comment": "", "albums": [], "profile_image_url": "https://upload.wikimedia.org/wikipedia/commons/e/ed/Eddie_Ng.JPG", "images_urls": [], "begin_date": { "$dateDay": "1965-06-07" }, "rating": 2.6666666666666665 }
