{ "name": "Mika Taanila", "gender": "Male", "area": "Finland", "deleted": false, "mbid": "16a0fc6d-ab3d-463e-bccb-b648990498a1", "_id": "16a0fc6d-ab3d-463e-bccb-b648990498a1", "slug_name": "mika-taanila", "slug_postfix": { "$numberLong": 0 }, "MBID": "16a0fc6d-ab3d-463e-bccb-b648990498a1", "disambiguation_comment": "", "albums": [], "profile_image_url": "https://upload.wikimedia.org/wikipedia/commons/7/7e/Mika_Taanila.JPG", "images_urls": [], "begin_date": { "$dateDay": "1965-01-01" }, "rating": 2.4 }
