{ "name": "Aaron Summers", "gender": "Male", "area": "South Jamaica", "deleted": false, "mbid": "232c1ff4-bbca-4852-8b9b-a4fb603414cb", "_id": "232c1ff4-bbca-4852-8b9b-a4fb603414cb", "slug_name": "aaron-summers", "slug_postfix": { "$numberLong": 0 }, "IPI": "00797780957", "MBID": "232c1ff4-bbca-4852-8b9b-a4fb603414cb", "disambiguation_comment": "rapper", "albums": [], "profile_image_url": "https://commons.wikimedia.org/wiki/File:Aaron_Summers.jpg", "images_urls": [], "begin_date": { "$dateDay": "1990-06-10" }, "rating": 2.7962962962962963 }
