{ "name": "Mette Lindberg", "gender": "Female", "area": "Denmark", "deleted": false, "mbid": "248966ea-bc31-4d8a-aac3-97fe7905be49", "_id": "248966ea-bc31-4d8a-aac3-97fe7905be49", "slug_name": "mette-lindberg", "slug_postfix": { "$numberLong": 0 }, "IPI": "00467447029", "MBID": "248966ea-bc31-4d8a-aac3-97fe7905be49", "disambiguation_comment": "", "albums": [], "profile_image_url": "https://commons.wikimedia.org/wiki/Category:Mette_Lindberg", "images_urls": [], "begin_date": { "$dateDay": "1983-12-02" }, "rating": 2.625 }
