{ "name": "S.COUPS", "gender": "Male", "area": "South Korea", "deleted": false, "mbid": "285c41b3-6a5d-48c7-8cd5-a25427765747", "_id": "285c41b3-6a5d-48c7-8cd5-a25427765747", "slug_name": "scoups", "slug_postfix": { "$numberLong": 0 }, "MBID": "285c41b3-6a5d-48c7-8cd5-a25427765747", "disambiguation_comment": "", "albums": [], "profile_image_url": "https://upload.wikimedia.org/wikipedia/commons/a/a4/S.Coups_-_2016_Gaon_Chart_K-pop_Awards_red_carpet.jpg", "images_urls": [], "begin_date": { "$dateDay": "1995-08-08" }, "rating": 2.7962962962962963 }
