{ "name": "B.J. Thomas", "gender": "Male", "area": "United States", "deleted": false, "mbid": "42a19448-ff60-4fd2-9d10-959bf2000729", "_id": "42a19448-ff60-4fd2-9d10-959bf2000729", "slug_name": "bj-thomas", "slug_postfix": { "$numberLong": 0 }, "MBID": "42a19448-ff60-4fd2-9d10-959bf2000729", "disambiguation_comment": "", "albums": [], "profile_image_url": "https://upload.wikimedia.org/wikipedia/commons/7/7a/B.J._Thomas_1972.JPG", "images_urls": [], "begin_date": { "$dateDay": "1942-08-07" }, "rating": 3.1285714285714286 }
