{ "name": "Alexander John Ellis", "gender": "Male", "area": "\\N", "deleted": false, "mbid": "4e70d99d-23ff-4b27-8abf-eaa484365c4c", "_id": "4e70d99d-23ff-4b27-8abf-eaa484365c4c", "slug_name": "alexander-john-ellis", "slug_postfix": { "$numberLong": 0 }, "ISNI": "000000010905760X", "MBID": "4e70d99d-23ff-4b27-8abf-eaa484365c4c", "disambiguation_comment": "", "albums": [], "profile_image_url": "https://upload.wikimedia.org/wikipedia/commons/9/98/Alexander_ellis.jpg", "images_urls": [], "begin_date": { "$dateDay": "1814-06-14" }, "end_date": { "$dateDay": "1890-10-28" }, "rating": 2.6216216216216215 }
