{ "name": "Nick Lachey", "gender": "Male", "area": "United States", "deleted": false, "mbid": "51eb1070-465f-4ec5-bbd9-2c3f4d82424f", "_id": "51eb1070-465f-4ec5-bbd9-2c3f4d82424f", "slug_name": "nick-lachey", "slug_postfix": { "$numberLong": 0 }, "IPI": "00342826660", "ISNI": "0000000078400953", "MBID": "51eb1070-465f-4ec5-bbd9-2c3f4d82424f", "disambiguation_comment": "", "albums": [], "profile_image_url": "https://upload.wikimedia.org/wikipedia/commons/f/f4/Nick_Lachey_3.jpg", "images_urls": [], "begin_date": { "$dateDay": "1973-11-09" }, "rating": 2.717391304347826 }
