{ "name": "Salvatore Accardo", "gender": "Male", "area": "Italy", "deleted": false, "mbid": "77e13fe3-a607-4ede-b94e-fa66d1050797", "_id": "77e13fe3-a607-4ede-b94e-fa66d1050797", "slug_name": "salvatore-accardo", "slug_postfix": { "$numberLong": 0 }, "ISNI": "0000000385044143", "MBID": "77e13fe3-a607-4ede-b94e-fa66d1050797", "disambiguation_comment": "", "albums": [], "profile_image_url": "https://upload.wikimedia.org/wikipedia/commons/f/f8/Salvatore_Accardo.jpg", "images_urls": [], "begin_date": { "$dateDay": "1941-09-26" }, "rating": 3.1956521739130435 }
