{ "name": "Mary Garden", "gender": "Female", "area": "Scotland", "deleted": false, "mbid": "8ea2558a-9f30-4e9f-9f74-2068f3eb2c00", "_id": "8ea2558a-9f30-4e9f-9f74-2068f3eb2c00", "slug_name": "mary-garden", "slug_postfix": { "$numberLong": 0 }, "ISNI": "0000000115620163", "MBID": "8ea2558a-9f30-4e9f-9f74-2068f3eb2c00", "disambiguation_comment": "", "albums": [], "profile_image_url": "https://commons.wikimedia.org/wiki/File:Mary_Garden_2.jpg", "images_urls": [], "begin_date": { "$dateDay": "1874-02-20" }, "end_date": { "$dateDay": "1967-01-03" }, "rating": 2.828125 }
