{ "name": "이기광", "gender": "Male", "area": "South Korea", "deleted": false, "mbid": "923465f2-351c-4da9-8933-811b05e1e745", "_id": "923465f2-351c-4da9-8933-811b05e1e745", "slug_name": "igigwang", "slug_postfix": { "$numberLong": 0 }, "MBID": "923465f2-351c-4da9-8933-811b05e1e745", "disambiguation_comment": "", "albums": [], "profile_image_url": "https://upload.wikimedia.org/wikipedia/commons/e/ea/Lee_Ki-kwang.jpg", "images_urls": [], "begin_date": { "$dateDay": "1990-03-30" }, "rating": 2.7666666666666666 }
