{ "name": "Peter Striebeck", "gender": "Male", "area": "Germany", "deleted": false, "mbid": "9988843d-51a5-4a22-afe0-10a39056b542", "_id": "9988843d-51a5-4a22-afe0-10a39056b542", "slug_name": "peter-striebeck", "slug_postfix": { "$numberLong": 0 }, "ISNI": "0000000044152613", "MBID": "9988843d-51a5-4a22-afe0-10a39056b542", "disambiguation_comment": "German actor", "albums": [], "profile_image_url": "https://upload.wikimedia.org/wikipedia/commons/6/62/Peter_StriebeckI.jpg", "images_urls": [], "begin_date": { "$dateDay": "1938-03-15" }, "rating": 2.883720930232558 }
