{ "name": "Henson Cargill", "gender": "Male", "area": "United States", "deleted": false, "mbid": "9cd0c8c6-e9c6-4bde-ae04-f4dbebb3b481", "_id": "9cd0c8c6-e9c6-4bde-ae04-f4dbebb3b481", "slug_name": "henson-cargill", "slug_postfix": { "$numberLong": 0 }, "IPI": "00126380979", "MBID": "9cd0c8c6-e9c6-4bde-ae04-f4dbebb3b481", "disambiguation_comment": "", "albums": [], "profile_image_url": "https://upload.wikimedia.org/wikipedia/commons/0/07/Henson_Cargill.png", "images_urls": [], "begin_date": { "$dateDay": "1941-02-05" }, "end_date": { "$dateDay": "2007-03-24" }, "rating": 3.435483870967742 }
