{ "name": "Gunter Schoß", "gender": "Male", "area": "Germany", "deleted": false, "mbid": "9d7eeee6-5f9c-4f99-8348-342f2bf65979", "_id": "9d7eeee6-5f9c-4f99-8348-342f2bf65979", "slug_name": "gunter-scho", "slug_postfix": { "$numberLong": 0 }, "MBID": "9d7eeee6-5f9c-4f99-8348-342f2bf65979", "disambiguation_comment": "German actor and voice actor", "albums": [], "profile_image_url": "https://commons.wikimedia.org/wiki/File:Gunter_Schoss.jpg", "images_urls": [], "begin_date": { "$dateDay": "1940-12-02" }, "rating": 2.7058823529411766 }
