{ "name": "Y’akoto", "gender": "Female", "area": "Germany", "deleted": false, "mbid": "9ff6febe-2e43-4d46-8011-667586c24cfc", "_id": "9ff6febe-2e43-4d46-8011-667586c24cfc", "slug_name": "yakoto", "slug_postfix": { "$numberLong": 0 }, "ISNI": "0000000457799175", "MBID": "9ff6febe-2e43-4d46-8011-667586c24cfc", "disambiguation_comment": "", "albums": [], "profile_image_url": "https://upload.wikimedia.org/wikipedia/commons/4/4e/Y%27akoto.jpg", "images_urls": [], "begin_date": { "$dateDay": "1988-01-01" }, "rating": 2.9038461538461537 }
