{ "name": "Clarence Cameron White", "gender": "Male", "area": "United States", "deleted": false, "mbid": "a9aa2394-3596-4651-a8fd-84fddc712cf9", "_id": "a9aa2394-3596-4651-a8fd-84fddc712cf9", "slug_name": "clarence-cameron-white", "slug_postfix": { "$numberLong": 0 }, "ISNI": "0000000081038086", "MBID": "a9aa2394-3596-4651-a8fd-84fddc712cf9", "disambiguation_comment": "", "albums": [], "profile_image_url": "https://upload.wikimedia.org/wikipedia/commons/d/d4/Maud_Cuney_Hare-Clarence_Cameron_White_329.jpg", "images_urls": [], "begin_date": { "$dateDay": "1880-08-10" }, "end_date": { "$dateDay": "1960-06-30" }, "rating": 3.0294117647058822 }
