{ "name": "Eckes Malz", "gender": "Male", "area": "Germany", "deleted": false, "mbid": "b57f82ab-c92d-4879-a5d8-e03792649f6a", "_id": "b57f82ab-c92d-4879-a5d8-e03792649f6a", "slug_name": "eckes-malz", "slug_postfix": { "$numberLong": 0 }, "IPI": "00241378869", "MBID": "b57f82ab-c92d-4879-a5d8-e03792649f6a", "disambiguation_comment": "", "albums": [], "profile_image_url": "https://upload.wikimedia.org/wikipedia/commons/5/51/EckesMalz.jpg", "images_urls": [], "begin_date": { "$dateDay": "1962-01-01" }, "rating": 2.5 }
