{ "name": "Louis Jordan", "gender": "Male", "area": "United States", "deleted": false, "mbid": "b8b30699-7814-4fd1-ab75-6f22f5da0fac", "_id": "b8b30699-7814-4fd1-ab75-6f22f5da0fac", "slug_name": "louis-jordan", "slug_postfix": { "$numberLong": 0 }, "MBID": "b8b30699-7814-4fd1-ab75-6f22f5da0fac", "disambiguation_comment": "American jazz, blues and rhythm & blues musician and songwriter", "albums": [], "profile_image_url": "https://upload.wikimedia.org/wikipedia/commons/c/c3/Louis_Jordan%2C_New_York%2C_N.Y.%2C_ca._July_1946_%28William_P._Gottlieb_04721%29.jpg", "images_urls": [], "begin_date": { "$dateDay": "1908-07-08" }, "end_date": { "$dateDay": "1975-02-04" }, "rating": 2.7142857142857144 }
