{ "name": "DeSchoWieda", "gender": "\\N", "area": "Germany", "deleted": false, "mbid": "c33864ec-51ff-48ae-850e-870a9d797b84", "_id": "c33864ec-51ff-48ae-850e-870a9d797b84", "slug_name": "deschowieda", "slug_postfix": { "$numberLong": 0 }, "MBID": "c33864ec-51ff-48ae-850e-870a9d797b84", "disambiguation_comment": "", "albums": [], "profile_image_url": "https://upload.wikimedia.org/wikipedia/commons/d/d7/DeSchoWieda-16.jpg", "images_urls": [], "begin_date": { "$dateDay": "2013-01-01" }, "rating": 2.875 }
