{ "name": "MGMT", "gender": "\\N", "area": "United States", "deleted": false, "mbid": "c485632c-b784-4ee9-8ea1-c5fb365681fc", "_id": "c485632c-b784-4ee9-8ea1-c5fb365681fc", "slug_name": "mgmt", "slug_postfix": { "$numberLong": 0 }, "ISNI": "0000000106610166", "MBID": "c485632c-b784-4ee9-8ea1-c5fb365681fc", "disambiguation_comment": "US pop rock group", "albums": [], "profile_image_url": "https://upload.wikimedia.org/wikipedia/commons/7/78/MGMT_a.jpg", "images_urls": [], "begin_date": { "$dateDay": "2002-12-01" }, "rating": 3.0428571428571427 }
