{ "name": "Nick Carter", "gender": "Male", "area": "United States", "deleted": false, "mbid": "d4c94cd6-dd98-48c2-b1d0-6d4620c350d5", "_id": "d4c94cd6-dd98-48c2-b1d0-6d4620c350d5", "slug_name": "nick-carter", "slug_postfix": { "$numberLong": 0 }, "IPI": "00341391188", "ISNI": "0000000055172791", "MBID": "d4c94cd6-dd98-48c2-b1d0-6d4620c350d5", "disambiguation_comment": "US pop singer & Backstreet Boy", "albums": [], "profile_image_url": "https://upload.wikimedia.org/wikipedia/commons/d/d8/Nick_Carter_2011.jpg", "images_urls": [], "begin_date": { "$dateDay": "1980-01-28" }, "rating": 2.7714285714285714 }
