{ "name": "Dark Green Tree", "gender": "\\N", "area": "Edinburgh", "deleted": false, "mbid": "d52c27ed-3023-4f18-81cd-050f7583046a", "_id": "d52c27ed-3023-4f18-81cd-050f7583046a", "slug_name": "dark-green-tree", "slug_postfix": { "$numberLong": 0 }, "MBID": "d52c27ed-3023-4f18-81cd-050f7583046a", "disambiguation_comment": "", "albums": [ { "cover_image_url": "http://coverartarchive.org/release/2bdbdbea-951a-4218-b38e-c689f8f08672/10774034592.jpg", "slug": "secret-lives-0", "name": "Secret lives", "id": "2bdbdbea-951a-4218-b38e-c689f8f08672" } ], "profile_image_url": "http://www.darkgreentree.com/photos/", "images_urls": [], "begin_date": { "$dateDay": "2014-03-01" }, "rating": 3.2241379310344827 }
