{ "name": "Francisco Manuel da Silva", "gender": "Male", "area": "Brazil", "deleted": false, "mbid": "d86c88d9-6781-40a0-bea2-f2d2438d5089", "_id": "d86c88d9-6781-40a0-bea2-f2d2438d5089", "slug_name": "francisco-manuel-da-silva", "slug_postfix": { "$numberLong": 0 }, "ISNI": "0000000081016514", "MBID": "d86c88d9-6781-40a0-bea2-f2d2438d5089", "disambiguation_comment": "", "albums": [], "profile_image_url": "https://upload.wikimedia.org/wikipedia/commons/1/18/Francisco_Manuel_da_Silva_by_Lu%C3%ADs_Aleixo_Boulanger.jpg", "images_urls": [], "begin_date": { "$dateDay": "1795-02-21" }, "end_date": { "$dateDay": "1865-12-18" }, "rating": 2.9523809523809526 }
