{ "name": "Unnikrishnan", "gender": "Male", "area": "India", "deleted": false, "mbid": "ec027ebc-c3fd-4fb5-aa29-f20bf36ee557", "_id": "ec027ebc-c3fd-4fb5-aa29-f20bf36ee557", "slug_name": "unnikrishnan", "slug_postfix": { "$numberLong": 0 }, "MBID": "ec027ebc-c3fd-4fb5-aa29-f20bf36ee557", "disambiguation_comment": "South Indian Classical & Playback Singer", "albums": [], "profile_image_url": "https://upload.wikimedia.org/wikipedia/commons/5/51/Unnikrishnan.jpg", "images_urls": [], "begin_date": { "$dateDay": "1964-07-09" }, "rating": 2.8043478260869565 }
