{ "name": "Liu Tian-Hua", "gender": "Male", "area": "China", "deleted": false, "mbid": "f39b7f71-4796-47bc-bb81-53e373a365ad", "_id": "f39b7f71-4796-47bc-bb81-53e373a365ad", "slug_name": "liu-tian-hua", "slug_postfix": { "$numberLong": 0 }, "MBID": "f39b7f71-4796-47bc-bb81-53e373a365ad", "disambiguation_comment": "erhu player and composer", "albums": [], "profile_image_url": "https://upload.wikimedia.org/wikipedia/commons/f/fc/%E5%88%98%E5%A4%A9%E5%8D%8E.jpg", "images_urls": [], "begin_date": { "$dateDay": "1895-02-04" }, "end_date": { "$dateDay": "1932-06-08" }, "rating": 2.789473684210526 }
