{ "name": "Leroy Sibbles", "gender": "Male", "area": "Jamaica", "deleted": false, "mbid": "f4ec94cd-2239-482b-8234-65a22ee9557c", "_id": "f4ec94cd-2239-482b-8234-65a22ee9557c", "slug_name": "leroy-sibbles", "slug_postfix": { "$numberLong": 0 }, "IPI": "00044373686", "ISNI": "0000000078395007", "MBID": "f4ec94cd-2239-482b-8234-65a22ee9557c", "disambiguation_comment": "", "albums": [], "profile_image_url": "https://upload.wikimedia.org/wikipedia/commons/a/a9/Leroy_Sibbles.jpg", "images_urls": [], "begin_date": { "$dateDay": "1949-01-29" }, "rating": 2.5384615384615383 }
