{ "name": "Kesha", "gender": "Female", "area": "United States", "deleted": false, "mbid": "fab34286-b8e1-4879-bce3-194e1358fbd2", "_id": "fab34286-b8e1-4879-bce3-194e1358fbd2", "slug_name": "kesha", "slug_postfix": { "$numberLong": 0 }, "IPI": "00472174848", "ISNI": "0000000114760658", "MBID": "fab34286-b8e1-4879-bce3-194e1358fbd2", "disambiguation_comment": "", "albums": [], "profile_image_url": "https://upload.wikimedia.org/wikipedia/commons/4/43/Ke%24ha_Today_Show_2012.jpg", "images_urls": [], "begin_date": { "$dateDay": "1987-03-01" }, "rating": 2.5869565217391304 }
